MB_package/__init__.py
MB_package/my_module.py
mb_package-0.0.2.dist-info/LICENSE
mb_package-0.0.2.dist-info/METADATA
mb_package-0.0.2.dist-info/WHEEL
mb_package-0.0.2.dist-info/top_level.txt
mb_package-0.0.2.dist-info/RECORD
